diffid/__init__.py
diffid/_diffid.cpython-311-x86_64-linux-gnu.so
diffid/_diffid.pyi
diffid/errors.py
diffid/py.typed
diffid/sampler.pyi
diffid/plotting/__init__.py
diffid/plotting/__init__.pyi
diffid.libs/libffi-00f593fe.so.8
diffid.libs/libtinfo-61f693cd.so.6
diffid.libs/libzstd-0a2128bc.so.1
diffid-0.3.0.dist-info/METADATA
diffid-0.3.0.dist-info/WHEEL
diffid-0.3.0.dist-info/RECORD
diffid-0.3.0.dist-info/licenses/LICENSE
