Metadata-Version: 2.4
Name: diffid
Version: 0.3.0
Classifier: Programming Language :: Rust
Classifier: Programming Language :: Python :: Implementation :: CPython
Classifier: Programming Language :: Python :: Implementation :: PyPy
Requires-Dist: numpy>=1.24.4
Requires-Dist: diffeqpy ; extra == 'diffeqpy'
Requires-Dist: jax==0.4.38 ; platform_machine == 'x86_64' and sys_platform == 'darwin' and extra == 'jax'
Requires-Dist: jaxlib==0.4.38 ; platform_machine == 'x86_64' and sys_platform == 'darwin' and extra == 'jax'
Requires-Dist: diffrax>=0.7.0 ; extra == 'jax'
Requires-Dist: matplotlib>=3.8 ; extra == 'plotting'
Provides-Extra: diffeqpy
Provides-Extra: jax
Provides-Extra: plotting
License-File: LICENSE
Requires-Python: >=3.11
